README.rst
setup.py
playrobot/Baidu.py
playrobot/IR.py
playrobot/LED_ring.py
playrobot/MQTT.py
playrobot/QA.py
playrobot/Raspi_I2C.py
playrobot/Raspi_MotorHAT.py
playrobot/Raspi_PWM_Servo_Driver.py
playrobot/Robots.py
playrobot/STT.py
playrobot/Servo.py
playrobot/TTS.py
playrobot/__init__.py
playrobot/dict.txt
playrobot/mecanumCtrl.py
playrobot/record.wav
playrobot/test2.mp3
playrobot/twcode.txt
playrobot.egg-info/PKG-INFO
playrobot.egg-info/SOURCES.txt
playrobot.egg-info/dependency_links.txt
playrobot.egg-info/requires.txt
playrobot.egg-info/top_level.txt