Metadata-Version: 1.2
Name: playrobot
Version: 0.0.28
Summary: lib for playrobot
Home-page: UNKNOWN
Author: ckshadow
Author-email: 99robot@playrobot.com
Maintainer: ckshadow
Maintainer-email: 99robot@playrobot.com
License: BSD License
Platform: all
Classifier: Development Status :: 4 - Beta
Classifier: Operating System :: OS Independent
Classifier: Intended Audience :: Developers
Classifier: License :: OSI Approved :: BSD License
Classifier: Programming Language :: Python
Classifier: Programming Language :: Python :: Implementation
Classifier: Programming Language :: Python :: 3
Classifier: Programming Language :: Python :: 3.4
Classifier: Programming Language :: Python :: 3.5
Classifier: Programming Language :: Python :: 3.6
Classifier: Topic :: Software Development :: Libraries
